specpart.cp311-win_amd64.dll.a
specpart.cp311-win_amd64.pyd
specpart-0.0.7.data/platlib/libgcc_s_seh-1-49d4426cec1f88bce8aececb363a51ca.dll
specpart-0.0.7.data/platlib/libgfortran-5-3411eb52eb86a1f4ba13e45b8c530e44.dll
specpart-0.0.7.data/platlib/libquadmath-0-02f5d4fd275bf93f299fba6393a71137.dll
specpart-0.0.7.data/platlib/libwinpthread-1-4643f5f9fec82525b7574401f2ae23f8.dll
specpart-0.0.7.dist-info/DELVEWHEEL
specpart-0.0.7.dist-info/LICENSE.txt
specpart-0.0.7.dist-info/METADATA
specpart-0.0.7.dist-info/RECORD
specpart-0.0.7.dist-info/WHEEL
