Metadata-Version: 2.1
Name: specpart
Version: 0.0.7
Summary: specpart module for use in wavespectra
Keywords: wave spectra ocean xarray statistics analysis
Author-Email: Wavespectra Developers <r.guedes@oceanum.science>
Maintainer-Email: Ruben de Bruin <info@rdbr.nl>
License: MIT License
Classifier: Development Status :: 5 - Production/Stable
Classifier: Intended Audience :: Science/Research
Classifier: License :: OSI Approved :: MIT License
Classifier: Natural Language :: English
Classifier: Operating System :: OS Independent
Classifier: Topic :: Scientific/Engineering
Classifier: Programming Language :: Python :: 3
Project-URL: Homepage, https://github.com/RubendeBruin/specpart
Project-URL: Issues, https://github.com/RubendeBruin/specpart/issues
Requires-Python: <3.12,>=3.8
